ak_frame_extractor/__init__.py
ak_frame_extractor/__main__.py
ak_frame_extractor/conf/dataset.conf
ak_frame_extractor/conf/frames_extractor.conf
ak_frame_extractor/conf/ui_frames_extractor.conf
dataset_management/__init__.py
dataset_management/dataset_config.py
dataset_management/dataset_manager.py
dataset_management/filename_decoder.py
dataset_management/pascal_voc_parser.py
dataset_management/test/__init__.py
dataset_management/test/test_dataset_config.py
dataset_management/test/test_dataset_manager.py
dataset_management/test/test_filename_decoder.py
dataset_management/test/test_pascal_voc_parser.py
dataset_management/test/test_suite_dataset_management.py
gui_frame_ext/__init__.py
gui_frame_ext/about_window.py
gui_frame_ext/gui_frame_ext_config.py
gui_frame_ext/gui_frame_ext_console.py
gui_frame_ext/temporal_data.py
gui_frame_ext/assets/ak_fraex_100.png
gui_frame_ext/assets/ak_fraex_32.png
gui_frame_ext/assets/logo_grap.png
helpers/__init__.py
helpers/helper_filesystem.py
helpers/helper_load_config.py
helpers/helper_validation.py
video_extraction_management/__init__.py
video_extraction_management/frame_extraction.py
video_extraction_management/frame_extraction_config.py
video_extraction_management/test/__init__.py
video_extraction_management/test/test_frame_extraction.py
video_extraction_management/test/test_frame_extraction_config.py
video_extraction_management/test/test_ka_real_time_video_extraction_2.py
video_extraction_management/test/test_suit_video_extraction.py
video_extraction_management/test/test_suite_video_management.py
video_extraction_management/video_helpers/__init__.py
video_extraction_management/video_helpers/helpers.py
ak_frame_extractor-1.3.dist-info/LICENSE
ak_frame_extractor-1.3.dist-info/METADATA
ak_frame_extractor-1.3.dist-info/WHEEL
ak_frame_extractor-1.3.dist-info/top_level.txt
ak_frame_extractor-1.3.dist-info/RECORD
