Metadata-Version: 2.1
Name: ak-frame-extractor
Version: 1.3
Summary: Python-based GUI tool to extract frames from video files produced with Azure Kinect cameras.
Home-page: https://github.com/GRAP-UdL-AT/ak_frame_extractor
Author: Juan Carlos Miranda, Jordi Gene-Mola, Jaume Arno, Eduard Gregorio
Author-email: juancarlos.miranda@udl.cat, jordi.genemola@udl.cat, jaume.arno@udl.cat, eduard.gregorio@udl.cat
Project-URL: Bug Tracker, https://github.com/GRAP-UdL-AT/ak_frame_extractor/issues
Classifier: Programming Language :: Python :: 3
Classifier: License :: OSI Approved :: MIT License
Classifier: Operating System :: OS Independent
Requires-Python: >=3.6
License-File: LICENSE
Requires-Dist: pip ==23.2.1
Requires-Dist: altgraph ==0.17.3
Requires-Dist: build ==0.10.0
Requires-Dist: colorama ==0.4.6
Requires-Dist: future ==0.18.3
Requires-Dist: lxml ==4.9.2
Requires-Dist: numpy ==1.24.2
Requires-Dist: opencv-python ==4.7.0.68
Requires-Dist: packaging ==23.0
Requires-Dist: pandas ==1.5.3
Requires-Dist: pefile ==2022.5.30
Requires-Dist: pep517 ==0.12.0
Requires-Dist: Pillow ==9.4.0
Requires-Dist: pyinstaller ==5.7.0
Requires-Dist: pyinstaller-hooks-contrib ==2022.15
Requires-Dist: pyk4a ==1.5.0
Requires-Dist: pyparsing ==3.0.9
Requires-Dist: python-dateutil ==2.8.2
Requires-Dist: python-version ==0.0.2
Requires-Dist: pytz ==2022.7.1
Requires-Dist: pywin32-ctypes ==0.2.0
Requires-Dist: scipy ==1.10.1
Requires-Dist: six ==1.16.0
Requires-Dist: tomli ==2.0.1
